xgclient/__init__.py
xgclient/client.py
xgclient-0.1.10.dist-info/METADATA
xgclient-0.1.10.dist-info/WHEEL
xgclient-0.1.10.dist-info/top_level.txt
xgclient-0.1.10.dist-info/RECORD
