Metadata-Version: 2.1
Name: xgclient
Version: 0.1.10
Summary: Python client for football (soccer) expected goals (xG) statistics API
Home-page: https://github.com/oRastor/xgclient
Author: Orest Bduzhak
Author-email: doom4eg@gmail.com
License: MIT
Keywords: football soccer xg expected-goals
Requires-Dist: requests (~=2.28.0)
Requires-Dist: marshmallow (~=3.16.0)
Requires-Dist: pandas (~=1.3.5)
Provides-Extra: dev
Requires-Dist: pytest ; extra == 'dev'
Requires-Dist: requests-mock ; extra == 'dev'
Requires-Dist: coverage ; extra == 'dev'
Requires-Dist: mypy ; extra == 'dev'
